cmfsage.py
cmfsage-0.0.6.dist-info/METADATA
cmfsage-0.0.6.dist-info/WHEEL
cmfsage-0.0.6.dist-info/top_level.txt
cmfsage-0.0.6.dist-info/RECORD
