Metadata-Version: 2.4
Name: cmfsage
Version: 0.0.6
Summary: This project is to enable common metadata framework logging for waggle sensor plugins: https://github.com/waggle-sensor.
Author: han.liu@hpe.com
Requires-Python: >=3.9
Requires-Dist: cmflib
Requires-Dist: pywaggle
Dynamic: author
Dynamic: requires-dist
Dynamic: requires-python
Dynamic: summary
